{
    "reference": "https://dichvucong.gov.vn/p/home/dvc-tthc-thu-tuc-hanh-chinh-chi-tiet.html?ma_thu_tuc=5323",
    "Mã thủ tục:": "1.003734",
    "Số quyết định:": "2108/QĐ-BGDĐT",
    "Tên thủ tục:": "Đăng ký dự thi cấp chứng chỉ ứng dụng công nghệ thông tin",
    "Cấp thực hiện:": "Cấp Bộ, Cấp Tỉnh",
    "Loại thủ tục:": "TTHC được luật giao quy định chi tiết",
    "Lĩnh vực:": "Thi, tuyển sinh",
    "Trình tự thực hiện:": "Bước 1: Cá nhân trực tiếp đến đăng ký với trung tâm sát hạch hoặc thông qua tổ chức để đăng ký dự thi với trung tâm sát hạch;Bước 2: Trung tâm sát hạch lập danh sách thí sinh.",
    "Cách thức thực hiện:": [
        {
            "Hình thức nộp": "Trực tiếp",
            "Thời hạn giải quyết": "Không quy định",
            "Phí, lệ phí": "",
            "Mô tả": "Theo thông báo của trung tâm sát hạch"
        },
        {
            "Hình thức nộp": "Trực tuyến",
            "Thời hạn giải quyết": "Không quy định",
            "Phí, lệ phí": "",
            "Mô tả": ""
        },
        {
            "Hình thức nộp": "Dịch vụ bưu chính",
            "Thời hạn giải quyết": "Không quy định",
            "Phí, lệ phí": "",
            "Mô tả": "Theo thông báo của trung tâm sát hạch"
        }
    ],
    "Thành phần hồ sơ:": {
        "Bao gồm": [
            {
                "Tên giấy tờ": "Đơn đăng ký dự thi theo mẫu tại Phụ lục kèm theo Thông tư liên tịch này",
                "Mẫu đơn, tờ khai": "",
                "Số lượng": "Bản chính: 1Bản sao: 0"
            },
            {
                "Tên giấy tờ": "Hai (02) ảnh 4cm×6cm theo kiểu ảnh chứng minh nhân dân được chụp không quá 06 tháng trước ngày đăng ký dự thi; mặt sau của ảnh ghi rõ họ và tên, ngày, tháng, năm sinh, nơi sinh",
                "Mẫu đơn, tờ khai": "",
                "Số lượng": "Bản chính: 2Bản sao: 0"
            },
            {
                "Tên giấy tờ": "Bản sao một trong các giấy tờ: chứng minh nhân dân, thẻ căn cước công dân, hộ chiếu hoặc giấy khai sinh kèm theo 01 giấy tờ có ảnh đóng dấu giáp lai.",
                "Mẫu đơn, tờ khai": "",
                "Số lượng": "Bản chính: 0Bản sao: 1"
            }
        ]
    },
    "Đối tượng thực hiện:": "Công dân Việt Nam, Người Việt Nam định cư ở nước ngoài, Người nước ngoài, Cán bộ, công chức, viên chức",
    "Cơ quan thực hiện:": "Trung tâm sát hạch",
    "Cơ quan có thẩm quyền:": "Không có thông tin",
    "Địa chỉ tiếp nhận HS:": "Trung tâm sát hạch hoặc tổ chức (Do CSDL không cho nhập trung tâm sát hạch và mục Cơ quan thực hiện nên tậm để là Cơ sở giáo dục phổ thông)",
    "Cơ quan được ủy quyền:": "Không có thông tin",
    "Cơ quan phối hợp:": "Không có thông tin",
    "Kết quả thực hiện:": "Danh sách thí sinh dự thi cấp chứng chỉ ứng dụng công nghệ thông tin",
    "Căn cứ pháp lý:": [
        {
            "Số ký hiệu": "17/2016/TTLT-BGDĐT-BTTTT",
            "Trích yếu": "Quy định tổ chức thi và cấp chứng chỉ ứng dụng công nghệ thông tin",
            "Ngày ban hành": "21-06-2016",
            "Cơ quan ban hành": "Bộ Giáo dục và Đào tạo"
        }
    ],
    "Yêu cầu, điều kiện thực hiện:": "Điều kiện dự thi\na) Cá nhân có hồ sơ đăng ký dự thi hợp lệ; đóng đầy đủ lệ phí thi theo quy định hiện hành;\nb) Thí sinh dự thi cấp chứng chỉ ứng dụng CNTT nâng cao phải có chứng chỉ ứng dụng CNTT cơ bản.",
    "Từ khóa:": "Không có thông tin",
    "Mô tả:": "Không có thông tin"
}