{
    "reference": "https://dichvucong.gov.vn/p/home/dvc-tthc-thu-tuc-hanh-chinh-chi-tiet.html?ma_thu_tuc=6364",
    "Mã thủ tục:": "2.001830",
    "Số quyết định:": "315/QĐ-BNV",
    "Tên thủ tục:": "Cấp Giấy phép làm việc cho công dân Ô-xtơ-rây-li-a tham gia Chương trình Lao động kết hợp kỳ nghỉ tại Việt Nam",
    "Cấp thực hiện:": "Cấp Bộ",
    "Loại thủ tục:": "TTHC không được luật giao cho địa phương quy định hoặc quy định chi tiết",
    "Lĩnh vực:": "Việc làm",
    "Trình tự thực hiện:": "Bước 1: Trước thời hạn ít nhất 30 ngày kể từ ngày dự kiến nhập cảnh vào Việt Nam, công dân Ô-xtơ-rây-li-a nộp hồ sơ đề nghị cấp Giấy phép cho cơ quan đại diện ngoại giao, cơ quan đại diện lãnh sự của Việt Nam tại Ô-xtơ-rây-li-a (sau đây viết tắt là Cơ quan đại diện của Việt Nam);Bước 2: Trong vòng 05 ngày làm việc kể từ ngày nhận đủ hồ sơ đề nghị cấp Giấy phép của công dân Ô-xtơ-rây-li-a, Cơ quan đại diện của Việt Nam chuyển hồ sơ đó qua đường thư điện tử hoặc fax đến Cục Việc làm;Bước 3: Trong thời hạn 07 ngày làm việc kể từ ngày nhận đủ hồ sơ đề nghị cấp Giấy phép làm việc từ Cơ quan đại diện của Việt Nam, Cục Việc làm thông báo kết quả cấp giấy phép làm việc hoặc không cấp phép làm việc cho Cơ quan đại diện của Việt Nam bằng văn bản.",
    "Cách thức thực hiện:": [
        {
            "Hình thức nộp": "Trực tiếp",
            "Thời hạn giải quyết": "12 Ngày làm việc",
            "Phí, lệ phí": "Lệ phí : 600000 Đồng Theo quy định tại Thông tư số 140/2016/TT-BTC ngày 19/9/2016 của Bộ Tài chính quy định mức thu, chế độ thu, nộp lệ phí cấp giấy phép làm việc trong kỳ nghỉ cho công dân Niu Di-Lân và công dân Ô-xtơ-rây-li-a",
            "Mô tả": "Công dân Ô-xtơ-rây-li-a nộp trực tiếp hoặc gửi qua dịch vụ bưu chính hoặc môi trường mạng (nếu đủ điều kiện áp dụng)."
        },
        {
            "Hình thức nộp": "Trực tuyến",
            "Thời hạn giải quyết": "12 Ngày làm việc",
            "Phí, lệ phí": "Lệ phí : 600000 Đồng Theo quy định tại Thông tư số 140/2016/TT-BTC ngày 19/9/2016 của Bộ Tài chính quy định mức thu, chế độ thu, nộp lệ phí cấp giấy phép làm việc trong kỳ nghỉ cho công dân Niu Di-Lân và công dân Ô-xtơ-rây-li-a",
            "Mô tả": "Công dân Ô-xtơ-rây-li-a nộp trực tiếp hoặc gửi qua dịch vụ bưu chính hoặc môi trường mạng (nếu đủ điều kiện áp dụng)."
        },
        {
            "Hình thức nộp": "Dịch vụ bưu chính",
            "Thời hạn giải quyết": "12 Ngày làm việc",
            "Phí, lệ phí": "Lệ phí : 600000 Đồng Theo quy định tại Thông tư số 140/2016/TT-BTC ngày 19/9/2016 của Bộ Tài chính quy định mức thu, chế độ thu, nộp lệ phí cấp giấy phép làm việc trong kỳ nghỉ cho công dân Niu Di-Lân và công dân Ô-xtơ-rây-li-a",
            "Mô tả": "Công dân Ô-xtơ-rây-li-a nộp trực tiếp hoặc gửi qua dịch vụ bưu chính hoặc môi trường mạng (nếu đủ điều kiện áp dụng)."
        }
    ],
    "Thành phần hồ sơ:": {
        "Bao gồm": [
            {
                "Tên giấy tờ": "Tờ khai đề nghị cấp Giấy phép làm việc kết hợp kỳ nghỉ (theo mẫu số 4 ban hành kèm theo Thông tư liên tịch số 21/2016/TTLT-BLĐTBXH-BCA-BNG ngày 29/6/2016)",
                "Mẫu đơn, tờ khai": "D:\\capstone-project\\forms\\viec_lam\\6Mus4BanhnhkmtheoThngtlintchs21_2016.pdf",
                "Số lượng": "Bản chính: 1Bản sao: 0"
            },
            {
                "Tên giấy tờ": "Hộ chiếu của công dân Ô-xtơ-rây-li-a còn thời hạn nhiều hơn 06 tháng tính từ thời điểm dự kiến tham gia Chương trình",
                "Mẫu đơn, tờ khai": "",
                "Số lượng": "Bản chính: 1Bản sao: 0"
            },
            {
                "Tên giấy tờ": "Có vé máy bay hoặc giấy tờ chứng minh có một khoản tiền đủ để mua vé máy bay",
                "Mẫu đơn, tờ khai": "",
                "Số lượng": "Bản chính: 1Bản sao: 0"
            },
            {
                "Tên giấy tờ": "Giấy chứng nhận sức khỏe được cấp không quá 12 tháng tính đến ngày nộp hồ sơ đề nghị cấp giấy phép làm việc",
                "Mẫu đơn, tờ khai": "",
                "Số lượng": "Bản chính: 1Bản sao: 0"
            },
            {
                "Tên giấy tờ": "Phiếu lý lịch tư pháp hoặc văn bản có giá trị tương đương được cấp không quá 06 tháng tính đến ngày nộp hồ sơ đề nghị cấp giấy phép làm việc",
                "Mẫu đơn, tờ khai": "",
                "Số lượng": "Bản chính: 1Bản sao: 0"
            },
            {
                "Tên giấy tờ": "Bằng tốt nghiệp trình độ đại học hoặc giấy tờ chứng minh đã hoàn thành ít nhất 02 năm đại học chính quy",
                "Mẫu đơn, tờ khai": "",
                "Số lượng": "Bản chính: 1Bản sao: 0"
            },
            {
                "Tên giấy tờ": "Thư giới thiệu của cơ quan có thẩm quyền của Chính phủ Ô-xtơ-rây-li-a đồng ý cho lưu trú tại Việt Nam theo các điều khoản của Chương trình. Giấy tờ quy định tại các khoản c.2, c.3, c.4, c.5, c.6 và c.7 là 01 bản sao và xuất trình bản chính để đối chiếu hoặc 01 bản sao được chứng thực từ bản chính.",
                "Mẫu đơn, tờ khai": "",
                "Số lượng": "Bản chính: 1Bản sao: 0"
            }
        ]
    },
    "Đối tượng thực hiện:": "Người nước ngoài",
    "Cơ quan thực hiện:": "Cục Việc làm",
    "Cơ quan có thẩm quyền:": "Cục Việc làm",
    "Địa chỉ tiếp nhận HS:": "Cục Việc làm",
    "Cơ quan được ủy quyền:": "Không có thông tin",
    "Cơ quan phối hợp:": "Không có thông tin",
    "Kết quả thực hiện:": "Cấp Giấy phép làm việc cho công dân Ô-xtơ-rây-li-a tham gia Chương trình Lao động kết hợp kỳ nghỉ tại Việt Nam",
    "Căn cứ pháp lý:": [
        {
            "Số ký hiệu": "21/2016/TTLT-BLĐTBXH-BCA-BNG",
            "Trích yếu": "Hướng dẫn thực hiện một số điều của Thỏa thuận giữa Chính phủ nước Cộng hòa xã hội chủ nghĩa Việt Nam và Chính phủ Ô-xtơ-rây-li-a về Chương trình Lao động kết hợp kỳ nghỉ",
            "Ngày ban hành": "29-06-2016",
            "Cơ quan ban hành": "Bộ Lao động - Thương binh và Xã hội"
        },
        {
            "Số ký hiệu": "190/2025/QH15",
            "Trích yếu": "Nghị quyết số 190/2025/QH15 của Quốc hội: Quy định về xử lý một số vấn đề liên quan đến sắp xếp tổ chức bộ máy nhà nước",
            "Ngày ban hành": "19-02-2025",
            "Cơ quan ban hành": "Quốc Hội"
        },
        {
            "Số ký hiệu": "Nghị định số 25/2025/NĐ-CP",
            "Trích yếu": "Nghị định số 25/2025/NĐ-CP ngày 21 tháng 02 năm 2025 của Chính phủ quy định chức năng, nhiệm vụ, quyền hạn và cơ cấu tổ chức của Bộ Nội vụ",
            "Ngày ban hành": "21-02-2025",
            "Cơ quan ban hành": "Chính phủ"
        }
    ],
    "Yêu cầu, điều kiện thực hiện:": "- Hộ chiếu của công dân Ô-xtơ-rây-li-a còn thời hạn nhiều hơn 06 tháng tính từ thời điểm dự kiến tham gia Chương trình;\n- Có vé máy bay hoặc giấy tờ chứng minh có một khoản tiền đủ để mua vé máy bay;\n- Giấy chứng nhận sức khỏe được cấp không quá 12 tháng tính đến ngày nộp hồ sơ đề nghị cấp giấy phép làm việc;\n- Phiếu lý lịch tư pháp hoặc văn bản có giá trị tương đương được cấp không quá 06 tháng tính đến ngày nộp hồ sơ đề nghị cấp giấy phép làm việc;\n- Bằng tốt nghiệp trình độ đại học hoặc giấy tờ chứng minh đã hoàn thành ít nhất 02 năm đại học chính quy.\n- Thư giới thiệu của cơ quan có thẩm quyền của Chính phủ Ô-xtơ-rây-li-a đồng ý cho lưu trú tại Việt Nam theo các điều khoản của Chương trình;\n- Hằng năm, cấp tối đa 200 Giấy phép làm việc cho công dân Ô-xtơ-rây-li-a đáp ứng được các điều kiện theo quy định.",
    "Từ khóa:": "Không có thông tin",
    "Mô tả:": "Không có thông tin"
}